{"chat_id":7,"chat_type":"Base","chat_users":[1,2,3],"messages_list":[{"sender_id":1,"sender_name":"Елфимов Андрей","sending_time":1716099599329,"message":"Ребята привет! тут мы решаем кодерские вопросы и помогаем друг другу)"},{"sender_id":2,"sender_name":"Coder 1 (Front)","sending_time":1716099892259,"message":"Всем привет!👋"},{"sender_id":3,"sender_name":"Coder 2 (Back)","sending_time":1716100126068,"message":"хорошо"}],"last_message":{"sender_id":3,"sender_name":"Coder 2 (Back)","sending_time":1716100126068,"message":"хорошо"}}